huehush/__init__.py
huehush-0.0.2.dist-info/LICENSE
huehush-0.0.2.dist-info/METADATA
huehush-0.0.2.dist-info/WHEEL
huehush-0.0.2.dist-info/top_level.txt
huehush-0.0.2.dist-info/RECORD
