Metadata-Version: 2.1
Name: huehush
Version: 0.0.2
Summary: huehush is a Python module that provides functionality to segment images into distinct clusters using the K-means clustering algorithm. This module is useful for tasks such as image segmentation, color quantization, and image compression.
Home-page: https://github.com/avd1729/hue-hush
Author: Aravind.M.S
Author-email: aravind19112003@gmail.com
License: Apache License 2.0
Requires-Python: >=3.8
License-File: LICENSE
Requires-Dist: numpy
Requires-Dist: matplotlib
Requires-Dist: scikit-learn
Requires-Dist: Pillow
